autoinit.py
autoinit-1.1.1.dist-info/LICENSE.md
autoinit-1.1.1.dist-info/METADATA
autoinit-1.1.1.dist-info/WHEEL
autoinit-1.1.1.dist-info/top_level.txt
autoinit-1.1.1.dist-info/RECORD
