Metadata-Version: 2.1
Name: autoinit
Version: 1.1.1
Summary: Python decorator for automatic initialization instance attributes
Author-email: Constantine Kosmachevski <oversider.kosma@gmail.com>
License: The MIT License (MIT)
Project-URL: Homepage, https://github.com/oversider-kosma/autoinit
Project-URL: Bug Tracker, https://github.com/oversider-kosma/autoinit/issues
Keywords: __init__,construcor,OOP,sugar
Classifier: Development Status :: 5 - Production/Stable
Classifier: License :: OSI Approved :: MIT License
Classifier: Programming Language :: Python
Classifier: Programming Language :: Python :: 2.7
Classifier: Programming Language :: Python :: 3
Classifier: Programming Language :: Python :: 3.5
Classifier: Programming Language :: Python :: 3.6
Classifier: Programming Language :: Python :: 3.7
Classifier: Programming Language :: Python :: 3.8
Classifier: Programming Language :: Python :: 3.9
Classifier: Programming Language :: Python :: 3.10
Classifier: Programming Language :: Python :: 3.11
Classifier: Programming Language :: Python :: Implementation :: CPython
Classifier: Programming Language :: Python :: Implementation :: PyPy
Classifier: Programming Language :: Python :: Implementation :: Jython
Classifier: Topic :: Software Development :: Libraries :: Python Modules
Classifier: Topic :: Utilities
Classifier: Operating System :: OS Independent
Requires-Python: >=2.7
License-File: LICENSE.md
